networkbilling/__init__.py
networkbilling/base.py
networkbilling/nsw/__init__.py
networkbilling/nsw/creditbalance.py
networkbilling/nsw/dispute.py
networkbilling/nsw/invoice.py
networkbilling/nsw/outstanding.py
networkbilling/nsw/remittance.py
networkbilling/nsw/statuschange.py
networkbilling/qld/__init__.py
networkbilling/qld/creditbalance.py
networkbilling/qld/dispute.py
networkbilling/qld/invoice.py
networkbilling/qld/outstanding.py
networkbilling/qld/remittance.py
networkbilling/qld/servicecharge.py
networkbilling/qld/statuschange.py
networkbilling/sa/__init__.py
networkbilling/sa/dispute.py
networkbilling/sa/invoice.py
networkbilling/sa/remittance.py
networkbilling/sa/servicecharge.py
networkbilling/vic/__init__.py
networkbilling/vic/dispute.py
networkbilling/vic/invoice.py
networkbilling/vic/remittance.py
networkbilling_EIGENMODE-0.1.12.dist-info/LICENSE
networkbilling_EIGENMODE-0.1.12.dist-info/METADATA
networkbilling_EIGENMODE-0.1.12.dist-info/WHEEL
networkbilling_EIGENMODE-0.1.12.dist-info/top_level.txt
networkbilling_EIGENMODE-0.1.12.dist-info/RECORD
