Metadata-Version: 2.1
Name: networkbilling-EIGENMODE
Version: 0.1.12
Summary: Parse and Verify Network Bill Files
Home-page: https://github.com/eigenmo-de/network-py
Author: Eric Sheppard
Author-email: eric@eigenmo.de
License: UNKNOWN
Platform: UNKNOWN
Classifier: Programming Language :: Python :: 3
Classifier: License :: OSI Approved :: MIT License
Classifier: Operating System :: OS Independent
Requires-Python: >=3.8
